Metadata-Version: 2.1
Name: bumbo-ekb
Version: 0.0.2
Summary: Bumbo Python Web Framework built for learning purposes.
Home-page: UNKNOWN
Author: Alexander Vakhov
Author-email: alex.vakhov@gmail.com
License: MIT
Platform: UNKNOWN
Classifier: Programming Language :: Python :: 3.6
Requires-Python: >=3.6.0
Requires-Dist: Jinja2 (==2.10.3)
Requires-Dist: parse (==1.14.0)
Requires-Dist: requests (==2.22.0)
Requires-Dist: requests-wsgi-adapter (==0.4.1)
Requires-Dist: WebOb (==1.8.6)
Requires-Dist: whitenoise (==5.0.1)
